MANIFEST.in
README.md
pyproject.toml
setup.py
omuse_qgmodel.egg-info/PKG-INFO
omuse_qgmodel.egg-info/SOURCES.txt
omuse_qgmodel.egg-info/dependency_links.txt
omuse_qgmodel.egg-info/requires.txt
omuse_qgmodel.egg-info/top_level.txt
src/omuse/community/qgmodel/Makefile
src/omuse/community/qgmodel/__init__.py
src/omuse/community/qgmodel/dijkstra2005.py
src/omuse/community/qgmodel/interface.f90
src/omuse/community/qgmodel/interface.py
src/omuse/community/qgmodel/plot_wind.py
src/omuse/community/qgmodel/run_qgmodel.py
src/omuse/community/qgmodel/test_bc.py
src/omuse/community/qgmodel/test_qgmodel.py
src/omuse/community/qgmodel/version.py
src/omuse/community/qgmodel/viebahn2014.py
src/omuse/community/qgmodel/src/Makefile
src/omuse/community/qgmodel/src/beta.f90
src/omuse/community/qgmodel/src/chi.f90
src/omuse/community/qgmodel/src/d_Poisson_2D_f.f90
src/omuse/community/qgmodel/src/d_Poisson_2D_f_fishpack.f90
src/omuse/community/qgmodel/src/jacobian.f90
src/omuse/community/qgmodel/src/main.f90
src/omuse/community/qgmodel/src/vis_bot.f90
src/omuse/community/qgmodel/src/vis_lat.f90
src/omuse/community/qgmodel/src/wind.f90
src/omuse/community/qgmodel/src/fishpack4.1/Makefile
src/omuse/community/qgmodel/src/fishpack4.1/doc/FISH.gif
src/omuse/community/qgmodel/src/fishpack4.1/doc/FISHPACK.html
src/omuse/community/qgmodel/src/fishpack4.1/doc/README_FISHPACK4.1
src/omuse/community/qgmodel/src/fishpack4.1/output/darwin.dp
src/omuse/community/qgmodel/src/fishpack4.1/output/darwin.sp
src/omuse/community/qgmodel/src/fishpack4.1/src/Makefile
src/omuse/community/qgmodel/src/fishpack4.1/src/blktri.f
src/omuse/community/qgmodel/src/fishpack4.1/src/cblktri.f
src/omuse/community/qgmodel/src/fishpack4.1/src/cmgnbn.f
src/omuse/community/qgmodel/src/fishpack4.1/src/comf.f
src/omuse/community/qgmodel/src/fishpack4.1/src/fftpack.f
src/omuse/community/qgmodel/src/fishpack4.1/src/genbun.f
src/omuse/community/qgmodel/src/fishpack4.1/src/gnbnaux.f
src/omuse/community/qgmodel/src/fishpack4.1/src/hstcrt.f
src/omuse/community/qgmodel/src/fishpack4.1/src/hstcsp.f
src/omuse/community/qgmodel/src/fishpack4.1/src/hstcyl.f
src/omuse/community/qgmodel/src/fishpack4.1/src/hstplr.f
